robotonotebook/.DS_Store
robotonotebook/__init__.py
robotonotebook/__init__.pyc
robotonotebook/static/css/robotonotebook.css
robotonotebook/static/img/.DS_Store
robotonotebook/static/img/bg-paper.png
robotonotebook/templates/.DS_Store
robotonotebook/templates/base.html
robotonotebook/templates/index.html
robotonotebook/templates/search_results.html
robotonotebook/templates/tools.html
robotonotebook/templates/blog/.DS_Store
robotonotebook/templates/blog/blog_post_detail.html
robotonotebook/templates/blog/blog_post_list.html
robotonotebook/templates/blog/includes/filter_panel.html
robotonotebook/templates/generic/comments.html
robotonotebook/templates/generic/includes/.DS_Store
robotonotebook/templates/generic/includes/comment.html
robotonotebook/templates/generic/includes/comments.html
robotonotebook/templates/includes/.DS_Store
robotonotebook/templates/includes/search_form.html
robotonotebook/templates/pages/.DS_Store
robotonotebook/templates/pages/index.html
robotonotebook/templates/pages/page.html
robotonotebook/templates/pages/menus/.DS_Store
robotonotebook/templates/pages/menus/breadcrumb.html
robotonotebook/templates/pages/menus/footer.html
robotonotebook/templates/pages/menus/tree.html
robotonotebook-0.0.1.post3.dist-info/DESCRIPTION.rst
robotonotebook-0.0.1.post3.dist-info/METADATA
robotonotebook-0.0.1.post3.dist-info/metadata.json
robotonotebook-0.0.1.post3.dist-info/RECORD
robotonotebook-0.0.1.post3.dist-info/top_level.txt
robotonotebook-0.0.1.post3.dist-info/WHEEL
