Metadata-Version: 2.0
Name: robotonotebook
Version: 0.0.1.post3
Summary: A Mezzanine CMS theme intended for publishing a personal blog with a minimalist design typeset with the Roboto typeface.
Home-page: https://github.com/hypertexthero/mezzanine-robotonotebook/
Author: Simon Griffee
Author-email: simongriffee@gmail.com
License: MIT
Platform: UNKNOWN
Classifier: Development Status :: 3 - Alpha
Classifier: Intended Audience :: Developers
Classifier: Natural Language :: English
Classifier: License :: OSI Approved :: MIT License
Classifier: Operating System :: OS Independent
Classifier: Programming Language :: Python
Classifier: Programming Language :: Python :: 2
Classifier: Programming Language :: Python :: 2.6
Classifier: Programming Language :: Python :: 2.7
Classifier: Programming Language :: Python :: 3
Classifier: Programming Language :: Python :: 3.3
Classifier: Topic :: Software Development :: Libraries :: Python Modules
Requires-Dist: Mezzanine
